<?xml version="1.0" encoding="UTF-8"?>
<!-- This example message is provided for illustrative purposes only. It has had no clinical validation nor is it guaranteed to be fully compliant with the written message specification. Where there are conflicts with the written message specification or schema, the specification or schema shall be considered to take precedence. -->
<EhrRequest xmlns="urn:hl7-org:v3" xmlns:fo="http://www.w3.org/1999/XSL/Format" xmlns:msg="urn:hl7-org:v3/mif" xmlns:voc="urn:hl7-org:v3/voc" xmlns:xsi="http://www.w3.org/2001/XMLSchema-instance" xsi:schemaLocation="urn:hl7-org:v3
../../Schemas/RCMR_MT010101UK03.xsd" classCode="EXTRACT" moodCode="RQO">
	<id root="BBBBA01A-A9D1-A411-F824-9F7A00A33757"/>
	<recordTarget typeCode="RCT">
		<patient classCode="PAT">
			<id root="2.16.840.1.113883.2.1.4.1" extension="9999999484"/>
		</patient>
	</recordTarget>
	<author typeCode="AUT">
		<AgentOrgSDS>
			<agentOrganizationSDS>
				<id root="1.2.826.0.1285.0.1.10" extension="Z99994"/>
			</agentOrganizationSDS>
		</AgentOrgSDS>
	</author>
	<destination typeCode="DST">
		<AgentOrgSDS classCode="AGNT">
			<agentOrganizationSDS classCode="ORG" determinerCode="INSTANCE">
				<id root="1.2.826.0.1285.0.1.10" extension="Z99993"/>
			</agentOrganizationSDS>
		</AgentOrgSDS>
	</destination>
</EhrRequest>
